vedit-0.0.3.dist-info/metadata.json
vedit-0.0.3.dist-info/METADATA
vedit-0.0.3.dist-info/LICENSE.txt
vedit-0.0.3.dist-info/WHEEL
vedit-0.0.3.dist-info/DESCRIPTION.rst
vedit-0.0.3.dist-info/RECORD
vedit-0.0.3.dist-info/top_level.txt
vedit/vedit.py
vedit/__init__.py
