Metadata-Version: 2.0
Name: vedit
Version: 0.0.3
Summary: Library for editing video by wrapping ffmpeg.
Home-page: https://github.com/digitalmacgyver/vedit
Author: Matthew Hayward
Author-email: mjhayward@gmail.com
License: MIT
Keywords: video ffmpeg
Platform: UNKNOWN
Classifier: Development Status :: 4 - Beta
Classifier: Programming Language :: Python
Classifier: Programming Language :: Python :: 2
Classifier: Programming Language :: Python :: 2.7
Classifier: Programming Language :: Python :: 3
Classifier: Environment :: Console
Classifier: Intended Audience :: Developers
Classifier: License :: OSI Approved :: MIT License
Classifier: Topic :: Multimedia :: Video
Classifier: Operating System :: POSIX
Classifier: Operating System :: MacOS
Classifier: Operating System :: Microsoft :: Windows
Classifier: Operating System :: POSIX :: Linux
Classifier: Topic :: Multimedia :: Graphics :: Editors
Classifier: Topic :: Multimedia :: Graphics
Classifier: Topic :: Multimedia
Classifier: Topic :: Multimedia :: Sound/Audio :: Mixers
Classifier: Topic :: Multimedia :: Video :: Conversion
Requires-Dist: future
